{"Country Office Website": "http://www.unicef.org/wcaro/Countries_1747.html", "Current Country Programme Document": "http://www.unicef.org/about/execboard/files/Chad_final_approved_2012-2016_20_Oct_2011.pdf", "CPD Extension": "", "Most Recent Annual Report": "http://www.unicef.org/about/annualreport/files/Chad_Annual_Report_2014.pdf", "document_links": [{"url": "https://www.unicef.org/chad/", "url_text": "Country Office Website"}, {"url": "http://www.unicef.org/about/execboard/files/Chad_CPD_Consolidated_Results_Report_Final.pdf", "url_text": "Chad Impact Appraisals"}, {"url": "http://www.unicef.org/supply/index_27009.html", "url_text": "Supply Tenders"}, {"url": "https://www.ungm.org/Public/ContractAward", "url_text": "Contracts"}, {"url": "http://www.unicef.org/about/partnerships/index_60043.html", "url_text": "Frameworks for Partnerships"}, {"url": "http://www.unicef.org/about/partnerships/index_60043.html", "url_text": "Frameworks for Partnerships"}, {"url": "https://www.unicef.org/about/execboard/files/2016-PL33-Chad-CPD-ODS-EN-8Aug16.pdf", "url_text": "Chad Country Programme Document"}, {"url": "http://www.unicef.org/evaldatabase/index_68314.html", "url_text": "Chad Evaluation Reports"}, {"url": "https://www.unicef.org/about/annualreport/files/Chad_2015_COAR_Final.pdf", "url_text": "Chad 2015 Annual Report"}]}