{"outputs": [{"sdt": "01-01-14", "otc_sfx": "004", "otc_id": 16393, "edt": "12-31-17", "dnr": {"all": 20080.0, "3527": 20080.0}, "sct": {"all": 21485.0, "PA06-03": 9811.0, "PA06-02": 11674.0}, "description": "By 2017, policymakers have access to an equity focused Situation Analysis on children in the KSA is available to guide nationalpolicies and programmes.", "pcr_id": "3780/A0/06/002", "b": 0, "as_of": "07-31-17"}, {"sdt": "01-01-14", "otc_sfx": "009", "as_of": "07-31-17", "edt": "12-31-17", "dnr": {}, "otc_id": 16357, "sct": {}, "pcr_id": "3780/A0/06/004", "b": 473000.0, "description": "description text"}, {"sdt": "01-01-12", "otc_sfx": "015", "otc_id": 16377, "edt": "12-31-13", "dnr": {"all": 75069.0, "3527": 75069.0}, "sct": {"all": 80324.0, "PA06-03": 36680.0, "PA06-02": 43644.0}, "description": "By 2013, policy makers and chilhdhood professionals in KSAhave a referrence study that assesses and analyses the situation ofchildren.", "pcr_id": "3780/A0/05/334", "b": 0, "as_of": "07-31-17"}, {"sdt": "01-01-14", "otc_sfx": "003", "otc_id": 16380, "edt": "12-31-17", "dnr": {"all": 57875.0, "3612": 57875.0}, "sct": {"PA06-07": 20915.0, "all": 60768.0, "PA06-03": 39853.0}, "description": "By 2017, policymakers have access to  a set of child rights Indicators for systematic generation of data to monitor the situationof children.", "pcr_id": "3780/A0/06/002", "b": 290000.0, "as_of": "07-31-17"}, {"sdt": "03-31-16", "otc_sfx": "013", "otc_id": 16385, "edt": "12-31-17", "dnr": {"all": 569.0, "3612": 569.0}, "sct": {"PA06-07": 205.0, "all": 597.0, "PA06-03": 392.0}, "description": "By 2017, the rights of children in the UAE are strengthened through a National Childhood Strategic Plan for the UAE (2017-2021)that is revised and approved by relevant authorities.", "pcr_id": "3780/A0/06/004", "b": 0, "as_of": "07-31-17"}, {"sdt": "01-01-14", "otc_sfx": "010", "otc_id": 16363, "edt": "12-31-17", "dnr": {"all": 21121.0, "3531": 21121.0}, "sct": {"all": 22177.0, "PA06-02": 22177.0}, "description": "By 2017, relevant government institutions in the UAE and KSA have been supported to conduct assessments of the child protectionsystem and to develop national plans to address priority gaps.", "pcr_id": "3780/A0/06/004", "b": 0, "as_of": "07-31-17"}, {"sdt": "01-01-14", "otc_sfx": "011", "otc_id": 16375, "edt": "12-31-17", "dnr": {"all": 66113.0, "3612": 66113.0}, "sct": {"PA06-07": 69419.0, "all": 69419.0}, "description": "By 2017, the rights of children with disability in the UAE are strengthened through the completion of a situation analysis andrelated national action plan.", "pcr_id": "3780/A0/06/004", "b": 0, "as_of": "07-31-17"}, {"sdt": "01-01-16", "otc_sfx": "016", "otc_id": 16403, "edt": "12-31-17", "dnr": {"all": 4649.0, "3612": 4649.0}, "sct": {"all": 4881.0, "PA07-04": 4881.0}, "description": "By 2017, the rights of children in urbanizing environments are promoted through the implementation and documentation of the ChildFriendly City initiative in at least one Emirate.", "pcr_id": "3780/A0/06/004", "b": 0, "as_of": "07-31-17"}, {"sdt": "01-01-14", "otc_sfx": "004", "otc_id": 16330, "edt": "12-31-17", "dnr": {"all": 245930.0, "3612": 125975.0, "3527": 119955.0}, "sct": {"all": 288646.0, "PA06-03": 288646.0}, "description": "By 2017, Ministry of Education and relevant partners have strengthened capacities to provide a safe learning environment forchildren.", "pcr_id": "3780/A0/06/004", "b": 0, "as_of": "07-31-17"}, {"sdt": "01-01-14", "otc_sfx": "007", "as_of": "07-31-17", "edt": "12-31-17", "dnr": {}, "otc_id": 16344, "sct": {}, "pcr_id": "3780/A0/06/004", "b": 250000.0, "description": "description text"}, {"sdt": "01-01-14", "otc_sfx": "006", "otc_id": 16336, "edt": "12-31-17", "dnr": {"273": 24.0, "all": 6346.0, "3612": 6322.0}, "sct": {"PA06-07": 2289.0, "all": 6664.0, "PA06-03": 4369.0, "PA06-02": 6.0}, "description": "By 2017, capacities of adolescents and young people to practice effective intrapersonal skills and healthy behaviors arestrengthened.", "pcr_id": "3780/A0/06/004", "b": 515000.0, "as_of": "07-31-17"}, {"sdt": "01-01-12", "otc_sfx": "004", "otc_id": 16303, "edt": "12-31-13", "dnr": {"all": 84777.0, "3527": 84777.0}, "sct": {"all": 90712.0, "PA06-02": 90712.0}, "description": "By 2013, national institutions and policy makers in KSA would have developed their national systems/procedures on child protectionand identified the gaps in child protection services.", "pcr_id": "3780/A0/05/333", "b": 0, "as_of": "07-31-17"}, {"sdt": "01-01-14", "otc_sfx": "001", "otc_id": 16370, "edt": "12-31-17", "dnr": {"all": 18995.0, "443": 18995.0}, "sct": {"PA06-07": 2993.0, "PA06-03": 12444.0, "all": 20514.0, "PA07-04": 210.0, "PA06-02": 4867.0}, "description": "Partnerships strengthened for effective programme delivery in the Gulf through policy dialogue, advocacy and innovation.", "pcr_id": "3780/A0/06/001", "b": 222000.0, "as_of": "07-31-17"}, {"sdt": "01-01-12", "otc_sfx": "006", "otc_id": 16283, "edt": "12-31-13", "dnr": {"all": -8.0, "3531": -8.0}, "sct": {"PA06-07": 110.0, "PA06-03": 458.0, "all": 755.0, "PA07-04": 8.0, "PA06-02": 179.0}, "description": "Salaries of programme and admin support staff", "pcr_id": "3780/A0/05/335", "b": 0, "as_of": "07-31-17"}, {"sdt": "01-01-14", "otc_sfx": "002", "as_of": "07-31-17", "edt": "12-31-17", "dnr": {}, "otc_id": 16409, "sct": {}, "pcr_id": "3780/A0/06/003", "b": 25000.0, "description": "description text"}, {"sdt": "01-01-12", "otc_sfx": "999", "otc_id": 645, "edt": "12-31-12", "dnr": {"all": 0}, "sct": {"PA06-07": 21118.0, "PA06-03": 87810.0, "all": 144755.0, "PA07-04": 1485.0, "PA06-02": 34342.0}, "description": "Prior-Year Commitments", "pcr_id": "3780/A0/05/800", "b": 0, "as_of": "07-31-17"}, {"sdt": "01-01-14", "otc_sfx": "001", "otc_id": 16400, "edt": "12-31-17", "dnr": {"all": 283297.0, "3531": 12748.0, "3612": 220989.0, "3527": 49560.0}, "sct": {"PA06-07": 84821.0, "PA06-03": 187421.0, "all": 298061.0, "PA07-04": 349.0, "PA06-02": 25470.0}, "description": "Costs related to program support staff.", "pcr_id": "3780/A0/06/003", "b": 317500.0, "as_of": "07-31-17"}, {"sdt": "01-01-14", "otc_sfx": "004", "otc_id": 16289, "edt": "12-31-17", "dnr": {"all": 27539.0, "3531": 6295.0, "3612": 1270.0, "3527": 19974.0}, "sct": {"PA06-07": 4483.0, "PA06-03": 17607.0, "all": 28917.0, "PA07-04": 283.0, "PA06-02": 6544.0}, "description": "Admin Support", "pcr_id": "3780/A0/06/003", "b": 0, "as_of": "07-31-17"}], "year": 2016}