{"outputs": [{"sdt": "01-01-15", "otc_sfx": "001", "otc_id": 30991, "edt": "12-31-17", "dnr": {"all": 168482.0, "2": 168482.0}, "sct": {"all": 168488.0, "PA05-05": 44623.0, "PA05-02": 1202.0, "PA05-01": 1424.0, "PA07-01": 3030.0, "PA07-02": 21707.0, "PA07-04": 14172.0, "PA07-05": 3334.0, "PA01-04": 7956.0, "PA06-07": 26729.0, "PA06-02": 44311.0}, "description": "Cross-Sectoral Support", "pcr_id": "1020/A0/05/881", "b": 70051.0, "as_of": "07-31-17"}, {"sdt": "01-01-13", "otc_sfx": "001", "otc_id": 30952, "edt": "12-31-17", "dnr": {"all": 233887.0, "2604": 16431.0, "2": 118678.0, "78": 2000.0, "30927": 2321.0, "18": 94457.0}, "sct": {"all": 241696.0, "PA05-05": 18938.0, "PA05-02": 2609.0, "PA05-03": 70.0, "PA05-01": 113.0, "PA07-01": 187.0, "PA07-02": 1337.0, "PA07-04": 1175.0, "PA07-05": 13108.0, "PA01-04": 490.0, "PA06-07": 200940.0, "PA06-02": 2729.0}, "description": "3.1.1 By 2017, the program will contribute with integration initiatives and programmatic coordination to raise awareness aboutpopulations that have been excluded and promote changes in behavior and knowledge.", "pcr_id": "1020/A0/05/004", "b": 244915.0, "as_of": "07-31-17"}, {"sdt": "01-01-13", "otc_sfx": "002", "otc_id": 30932, "edt": "12-31-17", "dnr": {"all": 208654.0, "186": 1849.0, "2604": 1932.0, "2": 171360.0, "149": 33513.0}, "sct": {"all": 214606.0, "PA06-02": 214606.0}, "description": "1.2.2 By 2017 the National Integrated Child Protection System (SNPI) has an established mechanism to monitor and evaluate itsperformance and results.", "pcr_id": "1020/A0/05/002", "b": 208654.0, "as_of": "07-31-17"}, {"sdt": "01-01-13", "otc_sfx": "001", "otc_id": 30924, "edt": "12-31-17", "dnr": {"all": 171206.0, "186": 21951.0, "2604": 58181.0, "2": 57217.0, "149": 33857.0}, "sct": {"PA06-07": 177389.0, "all": 177389.0}, "description": "1.2.1 By 2017, 20 cantons with the lowest welfare indicators have improved protection services against the different forms ofviolence for children and adolescents, in the family, the community and the school.", "pcr_id": "1020/A0/05/002", "b": 171205.0, "as_of": "07-31-17"}, {"sdt": "01-01-13", "otc_sfx": "001", "otc_id": 30968, "edt": "12-31-17", "dnr": {"all": 5400.0, "2": 5400.0}, "sct": {"all": 9330.0, "PA05-05": 2471.0, "PA05-02": 67.0, "PA05-01": 79.0, "PA07-01": 168.0, "PA07-02": 1202.0, "PA07-04": 785.0, "PA07-05": 185.0, "PA01-04": 440.0, "PA06-07": 1480.0, "PA06-02": 2453.0}, "description": "Effective and efficient governance and systems to manage risks and achieve programme results.", "pcr_id": "1020/A0/05/800", "b": 28608.0, "as_of": "07-31-17"}, {"sdt": "01-01-13", "otc_sfx": "003", "as_of": "07-31-17", "edt": "12-31-17", "dnr": {}, "otc_id": 30989, "sct": {}, "pcr_id": "1020/A0/05/800", "b": 16173.0, "description": "description text"}, {"sdt": "01-01-13", "otc_sfx": "002", "otc_id": 30974, "edt": "12-31-17", "dnr": {"all": 161.0, "2": 161.0}, "sct": {"all": 235.0, "PA05-05": 62.0, "PA05-02": 2.0, "PA05-01": 2.0, "PA07-01": 4.0, "PA07-02": 30.0, "PA07-04": 20.0, "PA07-05": 5.0, "PA01-04": 11.0, "PA06-07": 37.0, "PA06-02": 62.0}, "description": "Effective and efficient management and stewardship of financial resources related to office administration.", "pcr_id": "1020/A0/05/800", "b": 33300.0, "as_of": "07-31-17"}, {"sdt": "01-01-13", "otc_sfx": "001", "otc_id": 30981, "edt": "12-31-17", "dnr": {"all": 453870.0, "294": 19041.0, "2604": 113273.0, "2": 178723.0, "78": 124184.0, "30927": 18649.0}, "sct": {"all": 466548.0, "PA05-05": 400766.0, "PA05-02": 65266.0, "PA05-03": 516.0}, "description": "1.1.1 By 2017, an enhanced education system resulted in an increased number of children and adolescents living in regions with thegreatest social/education inequities that complete primary and secondary within the standard timeframes.", "pcr_id": "1020/A0/05/001", "b": 453967.0, "as_of": "07-31-17"}, {"sdt": "01-01-13", "otc_sfx": "002", "otc_id": 30995, "edt": "12-31-17", "dnr": {"all": 175624.0, "1797": 1797.0, "294": 26866.0, "2604": 448.0, "2": -9381.0, "78": -1282.0, "30927": 1506.0, "3604": 28415.0, "471": 127255.0}, "sct": {"all": 280438.0, "PA05-05": 45071.0, "PA05-02": 6577.0, "PA05-03": 118.0, "PA05-01": 139040.0, "PA07-01": 802.0, "PA07-02": 9608.0, "PA07-04": 4765.0, "PA07-05": 883.0, "PA01-04": 32899.0, "PA06-07": 25989.0, "PA06-02": 14686.0}, "description": "1.1.2 By 2017 in regions of greatest social exclusion, a targeted integrated early childhood development policy is applied,implemented by the relevant government agencies granting access to child care services for the most vulnerable children ages 0-7", "pcr_id": "1020/A0/05/001", "b": 175623.0, "as_of": "07-31-17"}, {"sdt": "01-01-13", "otc_sfx": "002", "otc_id": 30945, "edt": "12-31-17", "dnr": {"all": 48601.0, "18": 5018.0, "2604": 8920.0, "2": 34663.0}, "sct": {"all": 69634.0, "PA07-04": 69634.0}, "description": "2.1.2 By 2017, Costa Rican social sectors and civil society organizations have increased capacity to monitor equity-based resultsand undertake evidence-based advocacy.", "pcr_id": "1020/A0/05/003", "b": 53553.0, "as_of": "07-31-17"}, {"sdt": "01-01-13", "otc_sfx": "001", "otc_id": 30940, "edt": "12-31-17", "dnr": {"all": 135833.0, "2": 135833.0}, "sct": {"all": 233524.0, "PA05-05": 21556.0, "PA05-02": 581.0, "PA05-01": 688.0, "PA07-01": 13190.0, "PA07-02": 150892.0, "PA07-04": 6846.0, "PA07-05": 1610.0, "PA01-04": 3843.0, "PA06-07": 12912.0, "PA06-02": 21406.0}, "description": "2.1.1 By 2017, the Children and Adolescents' Information System (SINA) generates information that informs policy makers  for theformulation and revisions of legislations, public policies and programs targeted at reducing inequities .", "pcr_id": "1020/A0/05/003", "b": 493768.0, "as_of": "07-31-17"}, {"sdt": "01-01-12", "otc_sfx": "001", "otc_id": 30959, "edt": "12-31-12", "dnr": {"all": 0}, "sct": {"all": 2946.0, "PA05-05": 780.0, "PA05-02": 21.0, "PA05-01": 25.0, "PA07-01": 53.0, "PA07-02": 380.0, "PA07-04": 248.0, "PA07-05": 58.0, "PA01-04": 139.0, "PA06-07": 467.0, "PA06-02": 775.0}, "description": "Efficient and effective management systems", "pcr_id": "1020/A0/04/800", "b": 0, "as_of": "07-31-17"}], "year": 2015}