{"outputs": [{"sdt": "01-01-12", "otc_sfx": "002", "otc_id": 24020, "edt": "04-06-12", "dnr": {"all": 6200.0, "13": 6200.0}, "sct": {"all": 19830.0, "11220": 19830.0}, "description": "2.2 By 2015, Education system  meets international standards on ECD andCFS", "pcr_id": "4360/A0/04/005", "b": 0, "as_of": "08-31-17"}, {"sdt": "01-01-12", "otc_sfx": "001", "otc_id": 24014, "edt": "07-13-12", "dnr": {"0": 2100.0, "all": 2100.0}, "sct": {"all": 128660.0, "16062": 128660.0}, "description": "1.1 By 2013 evidence based budget allocations for national plans on pre-school and basic education and juvenile justice are increased and equitable", "pcr_id": "4360/A0/04/004", "b": 0, "as_of": "08-31-17"}, {"sdt": "01-01-12", "otc_sfx": "001", "otc_id": 23965, "edt": "12-31-15", "dnr": {"0": 280269.0, "all": 323611.0, "11": 9862.0, "66": 33480.0}, "sct": {"all": 311906.0, "16050": 44758.0, "12220": 267148.0}, "description": "By 2015, health system delivers quality service in mother and child health, in line with international standards", "pcr_id": "4360/A0/04/008", "b": 343876.0, "as_of": "08-31-17"}, {"sdt": "01-01-12", "otc_sfx": "002", "otc_id": 23972, "edt": "12-31-15", "dnr": {"0": 47568.0, "all": 372124.0, "778": 63539.0, "13": 261017.0}, "sct": {"11110": 304522.0, "all": 387350.0, "74010": 82828.0}, "description": "By 2015, Education system  meets international standards on ECD and CFS", "pcr_id": "4360/A0/04/008", "b": 309086.0, "as_of": "08-31-17"}, {"sdt": "01-01-12", "otc_sfx": "001", "otc_id": 24026, "edt": "03-07-12", "dnr": {"0": 3015.0, "all": 3015.0}, "sct": {"15150": 3015.0, "all": 3015.0}, "description": "Communication and operational costs against approved CPD programme budgets, donor plans and expenditure statements.", "pcr_id": "4360/A0/04/006", "b": 0, "as_of": "08-31-17"}, {"sdt": "01-01-12", "otc_sfx": "002", "otc_id": 24013, "edt": "04-06-12", "dnr": {"all": 0}, "sct": {"16010": 1241.0, "all": 1241.0}, "description": "By 2014, the state addresses gaps  related to children\u2019s legislation and rights and maintains national reporting function on the state of the children\u2019s rights", "pcr_id": "4360/A0/04/001", "b": 0, "as_of": "08-31-17"}, {"sdt": "01-01-12", "otc_sfx": "001", "otc_id": 24019, "edt": "04-13-12", "dnr": {"all": 0}, "sct": {"12110": 14893.0, "all": 14893.0}, "description": "By 2014, health system delivers high quality service, in line with international standards", "pcr_id": "4360/A0/04/005", "b": 0, "as_of": "08-31-17"}, {"sdt": "01-01-12", "otc_sfx": "002", "otc_id": 24006, "edt": "12-31-15", "dnr": {"0": 27200.0, "all": 27200.0}, "sct": {"all": 27200.0, "22010": 27200.0}, "description": "Joint UN activities", "pcr_id": "4360/A0/04/010", "b": 27200.0, "as_of": "08-31-17"}, {"sdt": "01-01-12", "otc_sfx": "003", "otc_id": 24024, "edt": "08-06-12", "dnr": {"all": 14960.0, "183": 14960.0}, "sct": {"all": 14960.0, "15261": 14960.0}, "description": "Relevant authorities detect, manage, refer and follow-up cases of abuse, exploitation and violence against children", "pcr_id": "4360/A0/04/005", "b": 0, "as_of": "08-31-17"}, {"sdt": "01-01-12", "otc_sfx": "003", "otc_id": 23975, "edt": "12-31-15", "dnr": {"0": 43119.0, "all": 154445.0, "180": 72848.0, "183": 38478.0}, "sct": {"16010": 158569.0, "all": 158569.0}, "description": "Relevant authorities administer policies in line with international standards  for vulnerable children", "pcr_id": "4360/A0/04/008", "b": 154444.0, "as_of": "08-31-17"}, {"sdt": "01-01-12", "otc_sfx": "001", "otc_id": 23985, "edt": "12-31-15", "dnr": {"0": 140529.0, "all": 140529.0}, "sct": {"all": 140529.0, "16062": 140529.0}, "description": "By 2015 evidence based budget allocations for national plans are increased and equitable", "pcr_id": "4360/A0/04/009", "b": 80531.0, "as_of": "08-31-17"}, {"sdt": "01-01-12", "otc_sfx": "001", "otc_id": 24002, "edt": "12-31-15", "dnr": {"0": 140686.0, "all": 140686.0}, "sct": {"all": 126958.0, "43010": 126958.0}, "description": "Operational support to programme implementation", "pcr_id": "4360/A0/04/010", "b": 140744.0, "as_of": "08-31-17"}, {"sdt": "01-01-12", "otc_sfx": "003", "otc_id": 23997, "edt": "12-31-15", "dnr": {"0": 55800.0, "all": 74345.0, "180": 18545.0}, "sct": {"all": 72685.0, "15152": 66303.0, "11240": 6382.0}, "description": "+Child rights knowledge                  target populations on child rights, gender,  life skills, and HIV prevention increased", "pcr_id": "4360/A0/04/009", "b": 74610.0, "as_of": "08-31-17"}, {"sdt": "01-01-12", "otc_sfx": "002", "otc_id": 23989, "edt": "12-31-15", "dnr": {"0": 58601.0, "all": 91636.0, "180": 33035.0}, "sct": {"all": 89864.0, "15110": 89864.0}, "description": "+Child rights legislation and reporting ed to children's legislation and rights and maintains national reporting function on thestate of the children's rights", "pcr_id": "4360/A0/04/009", "b": 91637.0, "as_of": "08-31-17"}], "year": 2012}