{"outputs": [{"sdt": "01-01-14", "otc_sfx": "003", "otc_id": 21937, "edt": "12-31-16", "dnr": {"all": 99011.0, "2": 53842.0, "294": 45169.0}, "sct": {"all": 106110.0, "PA05-03": 106110.0}, "description": "Low-cost innovations in teaching and learning of early literacy and numeracy skills piloted, researched and documented", "pcr_id": "6890/A0/05/303", "b": 0, "as_of": "07-31-17"}, {"sdt": "01-01-12", "otc_sfx": "002", "otc_id": 21898, "edt": "12-31-16", "dnr": {"73": 50363.0, "all": -66363.0, "18": -101392.0, "2": 2294.0, "23": -17628.0}, "sct": {"PA02-01": -7857.0, "all": 212360.0, "PA04-06": 33512.0, "PA04-02": 595.0, "PA01-05": 186110.0}, "description": "National policies reflect evidence based strategies to reduce child morbidity and mortality", "pcr_id": "6890/A0/05/101", "b": 0, "as_of": "07-31-17"}, {"sdt": "01-01-12", "otc_sfx": "004", "otc_id": 21875, "edt": "12-31-16", "dnr": {"all": 20442.0, "2": 20442.0}, "sct": {"all": 131545.0, "PA04-06": 6148.0, "PA07-02": 1039.0, "PA07-03": 5836.0, "PA07-04": 4351.0, "PA07-05": 6479.0, "PA06-07": 1869.0, "PA06-06": 1541.0, "PA06-05": 5596.0, "PA06-04": 7274.0, "PA06-03": 3581.0, "PA06-02": 273.0, "PA06-08": 4119.0, "PA04-05": 1109.0, "PA04-04": 551.0, "PA01-01": 631.0, "PA01-06": 37.0, "PA01-04": 7403.0, "PA01-05": 7283.0, "PA03-04": 2776.0, "PA03-05": 237.0, "PA03-06": 7915.0, "PA03-01": 2373.0, "PA03-02": 7265.0, "PA05-04": 1745.0, "PA05-05": 10925.0, "PA05-02": 7588.0, "PA05-03": 3554.0, "PA05-01": 7623.0, "PA01-03": 3601.0, "PA02-03": 680.0, "PA02-02": 7428.0, "PA02-01": 2715.0}, "description": "National systems are strengthened to collect, analyze and disseminate high quality data on the situation of children to supportadequate planning and investment", "pcr_id": "6890/A0/05/601", "b": 0, "as_of": "07-31-17"}, {"sdt": "01-01-17", "otc_sfx": "003", "otc_id": 22086, "edt": "12-31-20", "dnr": {"72": 118197.0, "73": 270026.0, "all": 1018223.0, "18": 170000.0, "2": 460000.0}, "sct": {"PA04-05": 1156.0, "all": 222718.0, "PA04-06": 215357.0, "PA04-01": 6205.0}, "description": "By 2020, service providers and communities have capacities to provide IYCF services", "pcr_id": "6890/A0/06/100", "b": 753262.0, "as_of": "07-31-17"}, {"sdt": "01-01-17", "otc_sfx": "002", "otc_id": 22074, "edt": "12-31-20", "dnr": {"all": 1225615.0, "1540": 45000.0, "72": 602052.0, "73": 107426.0, "2": 175000.0, "18": 192465.0, "23": 63672.0, "1087": 40000.0}, "sct": {"all": 196430.0, "PA04-06": 196430.0}, "description": "By 2020, evidence based national nutrition related policies, legislation, strategies, and plans are adopted and implementationmonitored", "pcr_id": "6890/A0/06/100", "b": 1702468.0, "as_of": "07-31-17"}, {"sdt": "01-01-17", "otc_sfx": "001", "otc_id": 22070, "edt": "12-31-20", "dnr": {"all": 1173821.0, "72": 513310.0, "73": 247140.0, "2": 54000.0, "15": 219450.0, "17": 56113.0, "18": 83808.0}, "sct": {"all": 252909.0, "PA04-06": 252909.0}, "description": "By 2020, strengthened sub-national level human and institutional capacities to coordinate, monitor and evaluate Government multi-sectoral, food and nutrition security policies and action plans", "pcr_id": "6890/A0/06/100", "b": 1116177.0, "as_of": "07-31-17"}, {"sdt": "01-01-12", "otc_sfx": "005", "otc_id": 21916, "edt": "12-31-16", "dnr": {"all": 14772.0, "2": 14772.0}, "sct": {"all": 39508.0, "PA07-03": 6750.0, "PA07-04": 32758.0}, "description": "Government plans and budgets are informed by child-focused data and information particularly in UNICEF target provinces of Zamb\u00e9ziaand Tete", "pcr_id": "6890/A0/05/601", "b": 0, "as_of": "07-31-17"}, {"sdt": "01-01-17", "otc_sfx": "001", "otc_id": 8635, "edt": "12-31-20", "dnr": {"all": 73.0, "2": 73.0}, "sct": {"all": 0}, "description": "Human Resources Management", "pcr_id": "6890/A0/06/800", "b": 0.0, "as_of": "07-31-17"}, {"sdt": "01-01-12", "otc_sfx": "001", "otc_id": 22142, "edt": "12-31-12", "dnr": {"all": -1121.0, "21744": 2.0, "18": -2190.0, "6163": 1.0, "3604": 5.0, "23": 1061.0}, "sct": {"all": -225.0, "PA04-02": -225.0}, "description": "MOZAMBIQUE CP 2007-2011", "pcr_id": "6890/DM/01/001", "b": 0.0, "as_of": "07-31-17"}, {"sdt": "01-01-17", "otc_sfx": "002", "otc_id": 716, "edt": "12-31-20", "dnr": {"72": 3000.0, "all": 3000.0}, "sct": {"all": 754.0, "PA03-06": 19.0, "PA03-02": 90.0, "PA03-01": 645.0}, "description": "External Relations", "pcr_id": "6890/A0/06/880", "b": 0.0, "as_of": "07-31-17"}, {"sdt": "01-01-17", "otc_sfx": "003", "otc_id": 22106, "edt": "12-31-20", "dnr": {"160": 344454.0, "450": 40000.0, "2": 940950.0, "all": 1606793.0, "658": 240000.0, "23": 41389.0}, "sct": {"all": 260242.0, "PA04-06": 12162.0, "PA07-02": 2056.0, "PA07-03": 11546.0, "PA07-04": 8609.0, "PA07-05": 12818.0, "PA06-07": 3697.0, "PA06-06": 3048.0, "PA06-05": 11071.0, "PA06-04": 14390.0, "PA06-03": 7084.0, "PA06-02": 541.0, "PA06-08": 8149.0, "PA04-05": 2194.0, "PA04-04": 1090.0, "PA01-01": 1248.0, "PA01-06": 73.0, "PA01-04": 14646.0, "PA01-05": 14408.0, "PA03-04": 5492.0, "PA03-05": 469.0, "PA03-06": 15659.0, "PA03-01": 4694.0, "PA03-02": 14372.0, "PA05-04": 3452.0, "PA05-05": 21614.0, "PA05-02": 15012.0, "PA05-03": 7031.0, "PA05-01": 15082.0, "PA01-03": 7124.0, "PA02-03": 1345.0, "PA02-02": 14695.0, "PA02-01": 5371.0}, "description": "Programme Planning and Monitoring: UNICEF staff and partners are provided guidance tools and resources to effectively plan andmonitor Programmes", "pcr_id": "6890/A0/06/880", "b": 810304.0, "as_of": "07-31-17"}, {"sdt": "01-01-17", "otc_sfx": "001", "otc_id": 701, "edt": "12-31-20", "dnr": {"160": 1794.0, "all": 101497.0, "1540": 23537.0, "450": 4200.0, "17": 6800.0, "18": 18500.0, "1785": 46666.0}, "sct": {"all": 0}, "description": "Programme Coordination", "pcr_id": "6890/A0/06/880", "b": 0.0, "as_of": "07-31-17"}, {"sdt": "01-01-17", "otc_sfx": "001", "otc_id": 22134, "edt": "12-31-20", "dnr": {"all": 7581723.0, "72": 626459.0, "73": 16620.0, "715": 329358.0, "2": 890000.0, "468": 9706.0, "23": 5156036.0, "24": 553544.0}, "sct": {"all": 5259989.0, "PA03-06": 5245537.0, "PA03-02": 14452.0}, "description": "By 2020, the capacity of the Government at national and decentralized levels in policy development, planning, monitoring,coordination, programme implementation, financial resource leveraging and budgeting for equitable and sustainable access to WASHservices at scale improved.", "pcr_id": "6890/A0/06/300", "b": 7745113.0, "as_of": "07-31-17"}, {"sdt": "01-01-17", "otc_sfx": "004", "otc_id": 5808, "edt": "12-31-20", "dnr": {"160": 50000.0, "all": 980666.0, "195": 40000.0, "72": 51500.0, "73": 135350.0, "2": 524000.0, "23": 82297.0, "24": 42123.0, "61": 6924.0, "1087": 48472.0}, "sct": {"all": 399753.0, "PA04-06": 74529.0, "PA04-01": 15798.0, "PA07-02": 1262.0, "PA07-03": 14577.0, "PA07-04": 33160.0, "PA07-05": 8757.0, "PA06-07": 2270.0, "PA06-06": 1872.0, "PA06-05": 11782.0, "PA06-04": 8834.0, "PA06-03": 9625.0, "PA06-02": 332.0, "PA01-05": 10189.0, "PA06-08": 5210.0, "PA04-05": 29506.0, "PA04-04": 4015.0, "PA01-01": 1830.0, "PA01-06": 45.0, "PA01-07": 7478.0, "PA01-04": 9715.0, "PA04-02": 9766.0, "PA03-04": 3372.0, "PA03-05": 2887.0, "PA03-06": 10805.0, "PA03-01": 3620.0, "PA03-02": 8824.0, "PA05-04": 2119.0, "PA05-05": 13270.0, "PA05-02": 9281.0, "PA05-03": 4317.0, "PA05-01": 9259.0, "PA01-03": 28359.0, "PA02-03": 826.0, "PA02-02": 38965.0, "PA02-01": 3297.0}, "description": "UNICEF staff and partners are provided tools, guidance and resources for effective advocacy and partnerships on child rights issueswith stakeholders", "pcr_id": "6890/A0/06/880", "b": 965000.0, "as_of": "07-31-17"}, {"sdt": "01-01-17", "otc_sfx": "005", "otc_id": 10994, "edt": "12-31-20", "dnr": {"all": 2805879.0, "195": 8000.0, "1540": 21745.0, "294": 392166.0, "72": 217240.0, "9": 13451.0, "11": 47429.0, "2": 1415500.0, "18": 253213.0, "21": 30000.0, "73": 7704.0, "23": 207596.0, "24": 105000.0, "1785": 5001.0, "715": 81834.0}, "sct": {"all": 1156338.0, "PA04-06": 42911.0, "PA04-01": 620.0, "PA07-02": 4474.0, "PA07-03": 24098.0, "PA07-04": 17949.0, "PA07-05": 26872.0, "PA06-07": 7758.0, "PA06-06": 6362.0, "PA06-05": 23473.0, "PA06-04": 30003.0, "PA06-03": 14817.0, "PA06-02": 1220.0, "PA01-05": 41003.0, "PA06-08": 17109.0, "PA04-05": 73798.0, "PA04-04": 3871.0, "PA01-01": 25389.0, "PA01-06": 424.0, "PA01-07": 99.0, "PA01-04": 58001.0, "PA04-02": 429.0, "PA03-04": 15997.0, "PA03-05": 15176.0, "PA03-06": 64032.0, "PA03-01": 95555.0, "PA03-02": 73761.0, "PA05-04": 11762.0, "PA05-05": 165940.0, "PA05-02": 76942.0, "PA05-03": 32528.0, "PA05-01": 123704.0, "PA01-03": 15611.0, "PA02-03": 2812.0, "PA02-02": 30662.0, "PA02-01": 11176.0}, "description": "Strategies to address cross-cutting issues related to child rights are developed and applied.", "pcr_id": "6890/A0/06/880", "b": 2091378.0, "as_of": "07-31-17"}, {"sdt": "01-01-17", "otc_sfx": "001", "otc_id": 22051, "edt": "12-31-20", "dnr": {"all": 1383931.0, "2": 848000.0, "294": 535930.0, "658": 1.0}, "sct": {"all": 352300.0, "PA05-01": 352300.0}, "description": "By 2020, policy makers have increased evidence on early learning and school readiness programmes, leveraging advocacy andresources to scale up.", "pcr_id": "6890/A0/06/400", "b": 1202806.0, "as_of": "07-31-17"}, {"sdt": "01-01-17", "otc_sfx": "004", "otc_id": 22122, "edt": "12-31-20", "dnr": {"450": 51377.0, "195": 1262445.0, "72": 116776.0, "2": 650000.0, "all": 2308692.0, "273": 382.0, "5560": 222499.0, "28": 5213.0}, "sct": {"PA02-02": 143926.0, "all": 143926.0}, "description": "By 2020, HIV positive pregnant and lactating women and children better adhere to HIV treatment and related services", "pcr_id": "6890/A0/06/200", "b": 1767683.0, "as_of": "07-31-17"}, {"sdt": "01-01-17", "otc_sfx": "001", "otc_id": 22126, "edt": "12-31-20", "dnr": {"450": 50000.0, "all": 457730.0, "28": 57730.0, "2": 350000.0}, "sct": {"all": 190568.0, "PA04-06": 7990.0, "PA07-02": 1351.0, "PA07-03": 7585.0, "PA07-04": 5655.0, "PA07-05": 8421.0, "PA06-07": 2429.0, "PA06-06": 2003.0, "PA06-05": 7273.0, "PA06-04": 9453.0, "PA06-03": 4654.0, "PA06-02": 355.0, "PA06-08": 5353.0, "PA04-05": 1441.0, "PA04-04": 716.0, "PA01-01": 820.0, "PA01-06": 48.0, "PA01-04": 9621.0, "PA01-05": 9465.0, "PA03-04": 3608.0, "PA03-05": 308.0, "PA03-06": 10287.0, "PA03-01": 3084.0, "PA03-02": 9442.0, "PA05-04": 2268.0, "PA05-05": 14199.0, "PA05-02": 9862.0, "PA05-03": 4619.0, "PA05-01": 9908.0, "PA01-03": 4680.0, "PA02-03": 20488.0, "PA02-02": 9654.0, "PA02-01": 3528.0}, "description": "By 2020, multisector coordination on adolescent-sensitive issues, evidence-based policies and strategies, with a focus on HIV/AIDS,are in place", "pcr_id": "6890/A0/06/600", "b": 805307.0, "as_of": "07-31-17"}, {"sdt": "01-01-17", "otc_sfx": "002", "otc_id": 22138, "edt": "12-31-20", "dnr": {"160": 350000.0, "149": 84718.0, "all": 4323207.0, "294": 59337.0, "72": 534361.0, "9": 11179.0, "11": 40000.0, "2": 1305000.0, "18": 124478.0, "21": 60105.0, "73": 685021.0, "23": 175945.0, "186": 180000.0, "2773": 186917.0, "28": 486146.0, "61": 20000.0, "1087": 20000.0}, "sct": {"all": 741524.0, "PA04-06": 39043.0, "PA04-01": 5755.0, "PA07-02": 6241.0, "PA07-03": 11903.0, "PA07-04": 8194.0, "PA07-05": 100285.0, "PA06-07": 20523.0, "PA06-06": 3039.0, "PA06-05": 76492.0, "PA06-04": 13698.0, "PA06-03": 71755.0, "PA06-02": 8823.0, "PA01-05": 27653.0, "PA06-08": 25538.0, "PA04-05": 39903.0, "PA04-04": 3218.0, "PA01-01": 27861.0, "PA01-06": 187.0, "PA01-07": 1128.0, "PA01-04": 23934.0, "PA04-02": 4591.0, "PA03-04": 5790.0, "PA03-05": 10445.0, "PA03-06": 40348.0, "PA03-01": 17851.0, "PA03-02": 16775.0, "PA05-04": 4284.0, "PA05-05": 23204.0, "PA05-02": 16889.0, "PA05-03": 7005.0, "PA05-01": 15969.0, "PA01-03": 7952.0, "PA02-03": 35683.0, "PA02-02": 14486.0, "PA02-01": 5079.0}, "description": "By 2020, disadvantaged children, adolescents and families have improved their knowledge and attitudes on key behaviour and socialnorms/practices on integrated sector priorities", "pcr_id": "6890/A0/06/600", "b": 3911462.0, "as_of": "07-31-17"}, {"sdt": "01-01-17", "otc_sfx": "003", "otc_id": 22152, "edt": "12-31-20", "dnr": {"160": 30000.0, "all": 1779926.0, "73": 50000.0, "2": 885000.0, "18": 8873.0, "28": 777345.0, "61": 28708.0}, "sct": {"all": 302470.0, "PA04-06": 5026.0, "PA07-02": 850.0, "PA07-03": 4771.0, "PA07-04": 3557.0, "PA07-05": 124161.0, "PA06-07": 1528.0, "PA06-06": 1260.0, "PA06-05": 12498.0, "PA06-04": 5946.0, "PA06-03": 4549.0, "PA06-02": 224.0, "PA06-08": 3697.0, "PA04-05": 907.0, "PA04-04": 450.0, "PA01-01": 516.0, "PA01-06": 30.0, "PA01-04": 6052.0, "PA01-05": 5954.0, "PA03-04": 2269.0, "PA03-05": 194.0, "PA03-06": 6471.0, "PA03-01": 1940.0, "PA03-02": 5939.0, "PA05-04": 1427.0, "PA05-05": 8932.0, "PA05-02": 6203.0, "PA05-03": 2906.0, "PA05-01": 6232.0, "PA01-03": 2944.0, "PA02-03": 66745.0, "PA02-02": 6073.0, "PA02-01": 2219.0}, "description": "By 2020, adolescents from selected youth groups, media networks and Child Parliament are increasingly aware of their rights toparticipation and engaged in child rights promotion", "pcr_id": "6890/A0/06/600", "b": 2298366.0, "as_of": "07-31-17"}, {"sdt": "01-01-12", "otc_sfx": "001", "otc_id": 21890, "edt": "12-31-16", "dnr": {"all": 2767540.0, "73": 2626.0, "2": 15282.0, "18": 993498.0, "21": 11002.0, "438": 46229.0, "23": 1683278.0, "61": 15625.0}, "sct": {"all": 282857.0, "PA01-05": 282857.0}, "description": "Health SWAp adequately supports implementation of national health plans", "pcr_id": "6890/A0/05/101", "b": 0, "as_of": "07-31-17"}, {"sdt": "01-01-12", "otc_sfx": "003", "otc_id": 21925, "edt": "12-31-16", "dnr": {"73": -2280.0, "all": 478206.0, "2": 480486.0}, "sct": {"all": 49172.0, "PA01-05": 49172.0}, "description": "Provincial health plans and budgets  are of good quality and prioritize interventions to reduce child morbidity and mortality", "pcr_id": "6890/A0/05/101", "b": 0, "as_of": "07-31-17"}, {"sdt": "01-01-17", "otc_sfx": "004", "otc_id": 22114, "edt": "12-31-20", "dnr": {"73": 60000.0, "all": 866000.0, "28": 40000.0, "2": 766000.0}, "sct": {"all": 94424.0, "PA06-04": 94424.0}, "description": "By 2020, strengthened legal framework and justice services adequately respond to children in contact or in conflict with the law", "pcr_id": "6890/A0/06/500", "b": 1515788.0, "as_of": "07-31-17"}, {"sdt": "01-01-17", "otc_sfx": "003", "otc_id": 22102, "edt": "12-31-20", "dnr": {"160": 58018.0, "all": 1882178.0, "73": 407200.0, "11": 187015.0, "2": 879000.0, "149": 130945.0, "28": 220000.0}, "sct": {"all": 363699.0, "PA06-03": 363699.0}, "description": "By 2020, strengthened multi-sectoral collaboration between government and civil society to prevent and address Violence againstChildren, child marriage and other harmful practices.", "pcr_id": "6890/A0/06/500", "b": 1817407.0, "as_of": "07-31-17"}, {"sdt": "01-01-17", "otc_sfx": "002", "otc_id": 22098, "edt": "12-31-20", "dnr": {"160": 436240.0, "all": 4702566.0, "1540": 354926.0, "73": 270236.0, "2": 950000.0, "18": 754319.0, "149": 50660.0, "23": 1702174.0, "61": 184011.0}, "sct": {"all": 1553516.0, "PA07-02": 775924.0, "PA06-08": 777592.0}, "description": "By 2020, a national child sensitive social protection strategy operationalised in six target provinces", "pcr_id": "6890/A0/06/500", "b": 4575954.0, "as_of": "07-31-17"}, {"sdt": "01-01-17", "otc_sfx": "001", "otc_id": 22090, "edt": "12-31-20", "dnr": {"160": 4735182.0, "all": 6393776.0, "21829": 63295.0, "2": 395000.0, "18": 556.0, "186": 1199743.0}, "sct": {"all": 1273036.0, "PA06-05": 1273036.0}, "description": "By 2020, a CRVS system is rolled out and operational nation-wide.", "pcr_id": "6890/A0/06/500", "b": 3820744.0, "as_of": "07-31-17"}, {"sdt": "01-01-15", "otc_sfx": "001", "otc_id": 22037, "edt": "12-31-16", "dnr": {"73": -26.0, "all": 294125.0, "2": 294717.0, "23": -566.0}, "sct": {"all": 159002.0, "PA04-06": 7459.0, "PA07-02": 1261.0, "PA07-03": 7081.0, "PA07-04": 5280.0, "PA07-05": 7862.0, "PA06-07": 2268.0, "PA06-06": 1870.0, "PA06-05": 6790.0, "PA06-04": 8826.0, "PA06-03": 4345.0, "PA06-02": 332.0, "PA06-08": 4998.0, "PA04-05": 1345.0, "PA04-04": 668.0, "PA01-01": 766.0, "PA01-06": 45.0, "PA01-04": 8528.0, "PA01-05": 8681.0, "PA03-04": 3368.0, "PA03-05": 288.0, "PA03-06": 9604.0, "PA03-01": 2879.0, "PA03-02": 8815.0, "PA05-04": 2117.0, "PA05-05": 13256.0, "PA05-02": 9207.0, "PA05-03": 4312.0, "PA05-01": 9250.0, "PA01-03": 4369.0, "PA02-03": 825.0, "PA02-02": 9013.0, "PA02-01": 3294.0}, "description": "UNICEF Capacity for Supply and Other Cross Sectoral Operations Costs", "pcr_id": "6890/A0/05/881", "b": 0, "as_of": "07-31-17"}, {"sdt": "01-01-15", "otc_sfx": "002", "otc_id": 22061, "edt": "12-31-16", "dnr": {"all": 222642.0, "2": 222642.0}, "sct": {"all": 161217.0, "PA04-06": 7534.0, "PA07-02": 1274.0, "PA07-03": 7152.0, "PA07-04": 5333.0, "PA07-05": 7941.0, "PA06-07": 2290.0, "PA06-06": 1888.0, "PA06-05": 6858.0, "PA06-04": 8914.0, "PA06-03": 4389.0, "PA06-02": 335.0, "PA06-08": 5048.0, "PA04-05": 1359.0, "PA04-04": 675.0, "PA01-01": 773.0, "PA01-06": 45.0, "PA01-04": 9073.0, "PA01-05": 8926.0, "PA03-04": 3402.0, "PA03-05": 290.0, "PA03-06": 9701.0, "PA03-01": 2908.0, "PA03-02": 8903.0, "PA05-04": 2139.0, "PA05-05": 13390.0, "PA05-02": 9300.0, "PA05-03": 4356.0, "PA05-01": 9343.0, "PA01-03": 4414.0, "PA02-03": 833.0, "PA02-02": 9104.0, "PA02-01": 3327.0}, "description": "UNICEF Capacity for Coordination and Cross Sectoral Programmatic Support", "pcr_id": "6890/A0/05/881", "b": 0, "as_of": "07-31-17"}, {"sdt": "01-01-12", "otc_sfx": "999", "otc_id": 432, "edt": "12-31-12", "dnr": {"8": 0.0, "all": 0.0}, "sct": {"all": 563.0, "PA05-02": 552.0, "PA04-02": 11.0}, "description": "PRIOR-YEAR COMMITMENTS", "pcr_id": "6890/DM/01/800", "b": 0.0, "as_of": "07-31-17"}, {"sdt": "01-01-17", "otc_sfx": "002", "otc_id": 22062, "edt": "12-31-20", "dnr": {"all": 1938833.0, "2": 693500.0, "294": 825333.0, "658": 420000.0}, "sct": {"all": 352915.0, "PA05-05": 352915.0}, "description": "By 2020, primary teachers have improved pedagogical competencies and are better motivated to produce effective learning of literacyand numeracy", "pcr_id": "6890/A0/06/400", "b": 3349371.0, "as_of": "07-31-17"}, {"sdt": "01-01-12", "otc_sfx": "009", "otc_id": 21930, "edt": "12-31-16", "dnr": {"all": 224567.0, "9": 86998.0, "2": 16439.0, "13": 6120.0, "18": 25520.0, "73": 57449.0, "23": 32041.0}, "sct": {"PA04-05": 366009.0, "all": 470219.0, "PA01-06": 2431.0, "PA01-04": 101779.0}, "description": "Morbidity and mortality caused by disasters are reduced through interventions before and during emergency", "pcr_id": "6890/A0/05/102", "b": 0, "as_of": "07-31-17"}, {"sdt": "01-01-12", "otc_sfx": "002", "otc_id": 21999, "edt": "12-31-16", "dnr": {"all": 260584.0, "294": 17107.0, "73": 83470.0, "2": 77801.0, "149": 31663.0, "21": 50543.0}, "sct": {"all": 137348.0, "PA04-06": 2253.0, "PA07-02": 381.0, "PA07-03": 9768.0, "PA07-04": 1594.0, "PA07-05": 2374.0, "PA06-07": 685.0, "PA06-06": 565.0, "PA06-05": 2051.0, "PA06-04": 2665.0, "PA06-03": 7998.0, "PA06-02": 100.0, "PA06-08": 4171.0, "PA04-05": 406.0, "PA04-04": 202.0, "PA01-01": 26633.0, "PA01-06": 14.0, "PA01-04": 2713.0, "PA01-05": 30207.0, "PA03-04": 1017.0, "PA03-05": 87.0, "PA03-06": 2900.0, "PA03-01": 869.0, "PA03-02": 2662.0, "PA05-04": 938.0, "PA05-05": 11975.0, "PA05-02": 5474.0, "PA05-03": 2481.0, "PA05-01": 8879.0, "PA01-03": 1320.0, "PA02-03": 249.0, "PA02-02": 2722.0, "PA02-01": 995.0}, "description": "By 2016, selected C4D government and CSO partners have enhanced their C4D capacity and are effectively supporting line Ministriesto manage focused and coordinated multi-level, multi-channel interventions with a focus on four priority provinces (2.5 CapacityDevelopment)", "pcr_id": "6890/A0/05/502", "b": 0, "as_of": "07-31-17"}, {"sdt": "01-01-12", "otc_sfx": "003", "otc_id": 22014, "edt": "12-31-16", "dnr": {"all": 233165.0, "294": 14178.0, "73": 65307.0, "2": 93460.0, "149": 3615.0, "23": 20309.0, "28": 36296.0}, "sct": {"all": 426173.0, "PA04-06": 23162.0, "PA04-01": 3964.0, "PA07-02": 896.0, "PA07-03": 4999.0, "PA07-04": 3727.0, "PA07-05": 91823.0, "PA06-07": 1602.0, "PA06-06": 1320.0, "PA06-05": 4804.0, "PA06-04": 6229.0, "PA06-03": 31979.0, "PA06-02": 237.0, "PA01-05": 31420.0, "PA06-08": 3531.0, "PA04-05": 27720.0, "PA04-04": 1228.0, "PA01-01": 4152.0, "PA01-06": 172.0, "PA01-07": 533.0, "PA01-04": 77080.0, "PA04-02": 2452.0, "PA03-04": 2378.0, "PA03-05": 2728.0, "PA03-06": 6809.0, "PA03-01": 2047.0, "PA03-02": 6226.0, "PA05-04": 1499.0, "PA05-05": 9435.0, "PA05-02": 6840.0, "PA05-03": 3055.0, "PA05-01": 6588.0, "PA01-03": 10196.0, "PA02-03": 36880.0, "PA02-02": 6362.0, "PA02-01": 2100.0}, "description": "By 2016 children, young people, women and their duty bearers are knowledgeable and address social norms that hamper the adoption ofkey selected life-saving, care and protective behaviours, paying special attention to reducing early pregnancy, child marriage,malnutrition, lack of sanitation, and HIV infection", "pcr_id": "6890/A0/05/502", "b": 0, "as_of": "07-31-17"}, {"sdt": "01-01-17", "otc_sfx": "003", "otc_id": 22055, "edt": "12-31-20", "dnr": {"149": 22783.0, "all": 367883.0, "2": 335000.0, "1087": 10100.0}, "sct": {"all": 135391.0, "PA07-03": 114935.0, "PA07-04": 20456.0}, "description": "By 2020, strengthened capacity of Local Governments to maximize the realization and promote equity for children in planning andbudgeting processes", "pcr_id": "6890/A0/06/700", "b": 635840.0, "as_of": "07-31-17"}, {"sdt": "01-01-17", "otc_sfx": "002", "otc_id": 22047, "edt": "12-31-20", "dnr": {"149": 205560.0, "all": 552567.0, "2": 345000.0, "61": 2007.0}, "sct": {"all": 220958.0, "PA07-03": 216941.0, "PA07-04": 4017.0}, "description": "By 2020, strengthened transparency, accountability and social oversight of national plans and budgets for inclusive socialpolicies", "pcr_id": "6890/A0/06/700", "b": 690805.0, "as_of": "07-31-17"}, {"sdt": "01-01-12", "otc_sfx": "002", "otc_id": 22007, "edt": "12-31-16", "dnr": {"all": 898086.0, "18": 11593.0, "2": 119022.0, "23": 767471.0}, "sct": {"PA01-03": 213197.0, "all": 2203867.0, "PA01-04": 1990670.0}, "description": "By 2015, all rural districts of Mozambique have community health workers trained and deployed to provide essential maternal,newborn and child health services.", "pcr_id": "6890/A0/05/102", "b": 0, "as_of": "07-31-17"}, {"sdt": "01-01-17", "otc_sfx": "004", "otc_id": 22066, "edt": "12-31-20", "dnr": {"160": 82776.0, "all": 601393.0, "1540": 140000.0, "73": 200000.0, "2": 177000.0, "23": 1064.0, "61": 553.0}, "sct": {"all": 105208.0, "PA07-02": 105208.0}, "description": "By 2020, strengthened capacity to develop and implement an evidence based child-sensitive and inclusive social protection policyframework", "pcr_id": "6890/A0/06/700", "b": 2087644.0, "as_of": "07-31-17"}, {"sdt": "01-01-14", "otc_sfx": "001", "otc_id": 21846, "edt": "12-31-16", "dnr": {"all": 340225.0, "2": 313098.0, "294": 27127.0}, "sct": {"all": 237335.0, "PA05-05": 13733.0, "PA05-03": 66550.0, "PA05-01": 157052.0}, "description": "Evidence-based strategic reforms and partnerships for improving quality and learning strengthened", "pcr_id": "6890/A0/05/303", "b": 0, "as_of": "07-31-17"}, {"sdt": "01-01-14", "otc_sfx": "001", "otc_id": 21997, "edt": "12-31-16", "dnr": {"1785": 1.0, "all": -2162.0, "294": -2163.0}, "sct": {"all": 53722.0, "PA05-05": 5046.0, "PA05-02": 48676.0}, "description": "Evidence-based multi-sectoral strategies for out-of-school children and mobilization for increased demand and community-action forequitable access to quality education with a special focus on adolescent girls", "pcr_id": "6890/A0/05/304", "b": 0, "as_of": "07-31-17"}, {"sdt": "01-01-12", "otc_sfx": "001", "otc_id": 21870, "edt": "12-31-16", "dnr": {"all": 131234.0, "28": 54013.0, "2": 77221.0}, "sct": {"all": 283824.0, "PA07-05": 283824.0}, "description": "By 2016, child participation spaces are strengthened and children from organized groups are empowered to speak for themselves  (1.1: C2C & Y2Y Media)", "pcr_id": "6890/A0/05/501", "b": 0, "as_of": "07-31-17"}, {"sdt": "01-01-12", "otc_sfx": "008", "otc_id": 21856, "edt": "12-31-16", "dnr": {"all": 0}, "sct": {"PA06-06": 89597.0, "all": 89597.0}, "description": "Government and community capacity to protect children affected by emergencies is strengthened, especially in emergency pronedistricts", "pcr_id": "6890/A0/05/402", "b": 0, "as_of": "07-31-17"}, {"sdt": "01-01-12", "otc_sfx": "002", "otc_id": 21910, "edt": "12-31-16", "dnr": {"all": 2639.0, "2": 2639.0}, "sct": {"all": 34924.0, "PA07-04": 34924.0}, "description": "By 2016, the Civil Society Forum for Child Rights and relevant children's networks are effectively equipped to engage in policyadvocacy and programme monitoring of child rights-related issues, with a focus on the meaningful participation of civil societyincluding children in decision making fora (1.2: Civil Society Participation)", "pcr_id": "6890/A0/05/501", "b": 0, "as_of": "07-31-17"}, {"sdt": "01-01-12", "otc_sfx": "001", "otc_id": 525, "edt": "12-31-16", "dnr": {"all": 0}, "sct": {"all": 328.0, "PA04-06": 15.0, "PA07-02": 3.0, "PA07-03": 14.0, "PA07-04": 11.0, "PA07-05": 16.0, "PA06-07": 5.0, "PA06-06": 4.0, "PA06-05": 14.0, "PA06-04": 18.0, "PA06-03": 9.0, "PA06-02": 1.0, "PA06-08": 10.0, "PA04-05": 3.0, "PA04-04": 1.0, "PA01-01": 2.0, "PA01-04": 18.0, "PA01-05": 18.0, "PA03-04": 7.0, "PA03-05": 1.0, "PA03-06": 20.0, "PA03-01": 6.0, "PA03-02": 18.0, "PA05-04": 4.0, "PA05-05": 27.0, "PA05-02": 19.0, "PA05-03": 9.0, "PA05-01": 19.0, "PA01-03": 9.0, "PA02-03": 2.0, "PA02-02": 18.0, "PA02-01": 7.0}, "description": "Effective and efficient Governance and Systems", "pcr_id": "6890/A0/05/800", "b": 0, "as_of": "07-31-17"}, {"sdt": "01-01-12", "otc_sfx": "002", "otc_id": 394, "edt": "12-31-16", "dnr": {"all": 0}, "sct": {"all": 11665.0, "PA04-06": 545.0, "PA07-02": 92.0, "PA07-03": 518.0, "PA07-04": 386.0, "PA07-05": 575.0, "PA06-07": 166.0, "PA06-06": 137.0, "PA06-05": 496.0, "PA06-04": 645.0, "PA06-03": 318.0, "PA06-02": 24.0, "PA06-08": 365.0, "PA04-05": 98.0, "PA04-04": 49.0, "PA01-01": 56.0, "PA01-06": 3.0, "PA01-04": 656.0, "PA01-05": 646.0, "PA03-04": 246.0, "PA03-05": 21.0, "PA03-06": 702.0, "PA03-01": 210.0, "PA03-02": 644.0, "PA05-04": 155.0, "PA05-05": 969.0, "PA05-02": 673.0, "PA05-03": 315.0, "PA05-01": 676.0, "PA01-03": 319.0, "PA02-03": 60.0, "PA02-02": 659.0, "PA02-01": 241.0}, "description": "Effective and efficient Management and Stewardship of Financial Resources", "pcr_id": "6890/A0/05/800", "b": 0, "as_of": "07-31-17"}, {"sdt": "01-01-17", "otc_sfx": "004", "otc_id": 22039, "edt": "12-31-20", "dnr": {"all": 626247.0, "18": 184303.0, "1540": 73603.0, "2": 175000.0, "23": 193341.0}, "sct": {"PA03-05": 6960.0, "all": 72573.0, "PA03-06": 65613.0}, "description": "By 2020, government has increased capacity to lead and coordinate Humanitarian WASH partnerships to meet the needs of the impactedpopulations", "pcr_id": "6890/A0/06/300", "b": 883727.0, "as_of": "07-31-17"}, {"sdt": "01-01-12", "otc_sfx": "003", "otc_id": 21750, "edt": "12-31-16", "dnr": {"160": 162206.0, "all": 400659.0, "1540": 77082.0, "73": 12103.0, "2": 69886.0, "18": 79382.0}, "sct": {"PA06-07": 206363.0, "all": 700092.0, "PA06-02": 493729.0}, "description": "Increased national capacity to provide access to effective social welfare systems including skilled workforce and case management", "pcr_id": "6890/A0/05/402", "b": 0, "as_of": "07-31-17"}, {"sdt": "01-01-12", "otc_sfx": "002", "otc_id": 22026, "edt": "12-31-16", "dnr": {"160": 31463.0, "all": 31463.0}, "sct": {"all": 123146.0, "PA07-02": 123146.0}, "description": "A child sensitive national social protection strategy is endorsed with coordinated support to strengthened Governmentinstitutional framework for knowledge management, implementation and monitoring", "pcr_id": "6890/A0/05/402", "b": 0, "as_of": "07-31-17"}, {"sdt": "01-01-12", "otc_sfx": "001", "otc_id": 21998, "edt": "12-31-16", "dnr": {"all": 0}, "sct": {"all": 10.0, "PA06-08": 10.0}, "description": "Programme operations effectively supported with appropriate human and material resources.", "pcr_id": "6890/A0/05/402", "b": 0, "as_of": "07-31-17"}, {"sdt": "01-01-17", "otc_sfx": "002", "otc_id": 22148, "edt": "12-31-20", "dnr": {"all": 9720069.0, "72": 5213366.0, "73": 120761.0, "715": 1419657.0, "2": 1180000.0, "658": 190000.0, "23": 178031.0, "24": 1406624.0, "186": 11630.0}, "sct": {"PA03-04": 61978.0, "all": 2837617.0, "PA03-06": 24901.0, "PA03-02": 21585.0, "PA03-01": 2729153.0}, "description": "By 2020, communities in target rural and peri-urban areas, small towns, schools and health centres, have access to sustainablewater services and scalable service delivery models.", "pcr_id": "6890/A0/06/300", "b": 9392049.0, "as_of": "07-31-17"}, {"sdt": "01-01-12", "otc_sfx": "007", "otc_id": 21830, "edt": "12-31-16", "dnr": {"160": 723184.0, "all": 754305.0, "186": 31121.0}, "sct": {"all": 994655.0, "PA06-05": 994655.0}, "description": "Increased percentage of children under five registered in health centres and communities and through newly endorsed eCRVS systemtested in 28 test sites", "pcr_id": "6890/A0/05/402", "b": 0, "as_of": "07-31-17"}, {"sdt": "01-01-12", "otc_sfx": "005", "otc_id": 21803, "edt": "12-31-16", "dnr": {"all": 9904.0, "18": 9904.0}, "sct": {"PA06-07": 51266.0, "all": 51266.0}, "description": "Children deprived of biological parental care provided with quality care and formally placed in alternative care families", "pcr_id": "6890/A0/05/402", "b": 0, "as_of": "07-31-17"}, {"sdt": "01-01-12", "otc_sfx": "004", "otc_id": 21776, "edt": "12-31-16", "dnr": {"73": 1853.0, "all": 1853.0}, "sct": {"PA06-07": 47499.0, "all": 47499.0}, "description": "Psychosocial support programmes implemented by government and civil society in a quality manner", "pcr_id": "6890/A0/05/402", "b": 0, "as_of": "07-31-17"}, {"sdt": "01-01-12", "otc_sfx": "004", "otc_id": 21886, "edt": "12-31-16", "dnr": {"all": 3488.0, "2": 3488.0}, "sct": {"PA06-07": 26585.0, "all": 26585.0}, "description": "Strategic partnerships are strengthened and social mobilisation intensified at all levels to prevent child marriage and violenceagainst children survey is undertaken", "pcr_id": "6890/A0/05/401", "b": 0, "as_of": "07-31-17"}, {"sdt": "01-01-12", "otc_sfx": "005", "otc_id": 21942, "edt": "12-31-16", "dnr": {"all": 171425.0, "2": 171425.0}, "sct": {"all": 146382.0, "PA06-04": 128351.0, "PA06-03": 14321.0, "PA06-02": 3710.0}, "description": "The capacity of  police, health, education and justice to respond to cases of violence, abuse, exploitation and neglect of childrenis strengthened", "pcr_id": "6890/A0/05/401", "b": 0, "as_of": "07-31-17"}, {"sdt": "01-01-12", "otc_sfx": "006", "otc_id": 21955, "edt": "12-31-16", "dnr": {"all": 0}, "sct": {"all": 47415.0, "PA06-04": 47415.0}, "description": "Improved legal framework and access to justice for children in contact and conflict with the law", "pcr_id": "6890/A0/05/401", "b": 0, "as_of": "07-31-17"}, {"sdt": "01-01-17", "otc_sfx": "001", "otc_id": 22043, "edt": "12-31-20", "dnr": {"149": 46830.0, "all": 1132392.0, "2": 1070000.0, "61": 15562.0}, "sct": {"all": 300857.0, "PA04-06": 9828.0, "PA07-02": 25558.0, "PA07-03": 32033.0, "PA07-04": 6957.0, "PA07-05": 10359.0, "PA06-07": 13351.0, "PA06-06": 2463.0, "PA06-05": 8946.0, "PA06-04": 11628.0, "PA06-03": 25387.0, "PA06-02": 437.0, "PA06-08": 19884.0, "PA04-05": 1773.0, "PA04-04": 881.0, "PA01-01": 1009.0, "PA01-06": 59.0, "PA01-04": 11835.0, "PA01-05": 11643.0, "PA03-04": 4438.0, "PA03-05": 379.0, "PA03-06": 12654.0, "PA03-01": 3793.0, "PA03-02": 11614.0, "PA05-04": 2790.0, "PA05-05": 17466.0, "PA05-02": 12763.0, "PA05-03": 5682.0, "PA05-01": 12188.0, "PA01-03": 5757.0, "PA02-03": 1087.0, "PA02-02": 11875.0, "PA02-01": 4340.0}, "description": "By 2020, quality research, analyses and evaluation on multiple dimensions of child poverty and deprivations inform policies andstrategies for inclusive and equitable development", "pcr_id": "6890/A0/06/700", "b": 1369095.0, "as_of": "07-31-17"}, {"sdt": "01-01-17", "otc_sfx": "001", "otc_id": 22094, "edt": "12-31-20", "dnr": {"all": 2155297.0, "195": 13952.0, "72": 102699.0, "73": 220810.0, "2": 630000.0, "18": 488676.0, "23": 56000.0, "1087": 643160.0}, "sct": {"PA01-03": 192804.0, "all": 199274.0, "PA04-01": 6470.0}, "description": "By 2020,  primary health care facilities have increased capacity to deliver quality integrated maternal and newborn health services", "pcr_id": "6890/A0/06/200", "b": 1806554.0, "as_of": "07-31-17"}, {"sdt": "01-01-17", "otc_sfx": "002", "otc_id": 22110, "edt": "12-31-20", "dnr": {"all": 8061056.0, "34": 153920.0, "72": 201776.0, "73": 316877.0, "2": 450000.0, "658": 179281.0, "450": 21000.0, "17": 785800.0, "18": 2546875.0, "21": 1672274.0, "438": 167819.0, "23": 1402401.0, "28": 15457.0, "61": 147576.0}, "sct": {"all": 558008.0, "PA01-03": 4215.0, "PA01-01": 266443.0, "PA01-06": 2932.0, "PA01-07": 266382.0, "PA01-04": 18036.0}, "description": "By 2020, health workers at facility and community level are better equipped to provide and stimulate  demand for  qualityintegrated child health services", "pcr_id": "6890/A0/06/200", "b": 5456725.0, "as_of": "07-31-17"}, {"sdt": "01-01-17", "otc_sfx": "003", "otc_id": 22118, "edt": "12-31-20", "dnr": {"all": 4335241.0, "1540": 399167.0, "72": 268568.0, "9": 50000.0, "11": 140000.0, "2": 81780.0, "15": 5000.0, "18": 922905.0, "21": 47666.0, "73": 1026782.0, "23": 1214484.0, "61": 26889.0, "1087": 152000.0}, "sct": {"PA04-05": 309606.0, "PA04-04": 59354.0, "all": 368960.0}, "description": "By 2020, health workers at community and primary care level have increased capacity to identify, enroll  and treat children withsevere acute malnutrition", "pcr_id": "6890/A0/06/200", "b": 3544604.0, "as_of": "07-31-17"}, {"sdt": "01-01-12", "otc_sfx": "001", "otc_id": 21998, "edt": "12-31-16", "dnr": {"all": -1343.0, "186": 11311.0, "149": -12654.0}, "sct": {"all": -13491.0, "PA07-03": -6063.0, "PA06-03": -5313.0, "PA06-08": -2115.0}, "description": "Programme operations effectively supported with appropriate human and material resources.", "pcr_id": "6890/A0/05/202", "b": 0, "as_of": "07-31-17"}, {"sdt": "01-01-17", "otc_sfx": "005", "otc_id": 22130, "edt": "12-31-20", "dnr": {"all": 5687028.0, "195": 50000.0, "72": 411652.0, "73": 22482.0, "2": 1008409.0, "17": 109200.0, "18": 2454705.0, "21": 97676.0, "23": 1532904.0}, "sct": {"all": 493581.0, "PA04-06": 368.0, "PA01-05": 493213.0}, "description": "By 2020, capacity of the health system to plan, finance and monitor core RMNCAH interventions, with a focus on community levelworkforce and supplies, is improved", "pcr_id": "6890/A0/06/200", "b": 5676425.0, "as_of": "07-31-17"}, {"sdt": "01-01-12", "otc_sfx": "003", "otc_id": 21793, "edt": "12-31-16", "dnr": {"all": 1102.0, "715": 682.0, "2": 420.0}, "sct": {"PA03-04": 67512.0, "all": 67512.0}, "description": "100,000 students from primary schools in targeted districts have improved water and sanitation services and hygiene education", "pcr_id": "6890/A0/05/202", "b": 0, "as_of": "07-31-17"}, {"sdt": "01-01-12", "otc_sfx": "005", "otc_id": 21809, "edt": "12-31-16", "dnr": {"17": 88089.0, "all": 425401.0, "438": 48562.0, "73": 288750.0}, "sct": {"all": 715169.0, "PA04-06": 272133.0, "PA04-01": 118318.0, "PA04-02": 324718.0}, "description": "By 2015, progress achieved in key areas of the Multisectoral Action Plan for the Reduction of Chronic Undernutrition, specificallyinfant and young child feeding and vitamin A supplementation/deworming", "pcr_id": "6890/A0/05/102", "b": 0, "as_of": "07-31-17"}, {"sdt": "01-01-14", "otc_sfx": "005", "otc_id": 21866, "edt": "12-31-16", "dnr": {"72": -1.0, "all": 31299.0, "2": 31300.0}, "sct": {"all": 156885.0, "PA03-01": 89098.0, "PA03-02": 67787.0}, "description": "In small towns, at least 100,000 new users, prioritising vulnerable groups, use safe water and 100,000 use safe sanitation andimproved hygiene practices", "pcr_id": "6890/A0/05/202", "b": 0, "as_of": "07-31-17"}, {"sdt": "01-02-14", "otc_sfx": "004", "otc_id": 21819, "edt": "12-31-16", "dnr": {"24": 24702.0, "all": 59216.0, "715": 31564.0, "468": 2950.0}, "sct": {"all": 76532.0, "PA03-06": 19503.0, "PA03-02": 55110.0, "PA03-01": 1919.0}, "description": "In rural areas, at least 300,000 new users, prioritising vulnerable groups, use safe water and 300,000 people use safe sanitationand improved hygiene practices", "pcr_id": "6890/A0/05/202", "b": 0, "as_of": "07-31-17"}, {"sdt": "01-01-12", "otc_sfx": "003", "otc_id": 21833, "edt": "12-31-16", "dnr": {"all": 16202.0, "2": 16202.0}, "sct": {"all": 52923.0, "PA07-03": 11317.0, "PA07-04": 41606.0}, "description": "Child-focused investments are bolstered by strong and equitable national plans and budgets, legislative scrutiny and advocacy.", "pcr_id": "6890/A0/05/601", "b": 0, "as_of": "07-31-17"}, {"sdt": "01-01-14", "otc_sfx": "002", "otc_id": 22022, "edt": "12-31-16", "dnr": {"all": 79846.0, "2": 52155.0, "294": 27691.0}, "sct": {"all": 536950.0, "PA05-05": 273327.0, "PA05-02": 214285.0, "PA05-04": 46177.0, "PA05-03": 3161.0}, "description": "Capacity at national and sub-national level developed  for multi-dimensional education planning and budgeting and for tracking ofand response to out-of-school children with a special focus on adolescent girls", "pcr_id": "6890/A0/05/304", "b": 0, "as_of": "07-31-17"}, {"sdt": "01-01-17", "otc_sfx": "003", "otc_id": 22032, "edt": "12-31-20", "dnr": {"all": 3695582.0, "715": 556871.0, "72": 1300741.0, "73": 35899.0, "11": 121989.0, "2": 840000.0, "658": 230000.0, "24": 610082.0}, "sct": {"PA03-04": 113248.0, "all": 847304.0, "PA07-03": 1281.0, "PA03-06": 15502.0, "PA03-02": 717273.0}, "description": "By 2020, communities in target rural and peri-urban areas, small towns, schools and health centres, achieve open defecation freestatus, with increased access to adequate sanitation services, improved hygiene practices.", "pcr_id": "6890/A0/06/300", "b": 3251492.0, "as_of": "07-31-17"}, {"sdt": "01-02-14", "otc_sfx": "006", "otc_id": 21909, "edt": "12-31-16", "dnr": {"all": 2834745.0, "9": 37214.0, "2": 1405872.0, "13": 1555.0, "18": 474409.0, "23": 823906.0, "28": 91789.0}, "sct": {"PA03-05": 255325.0, "all": 255325.0}, "description": "Humanitarian action - Preparedness and response in emergency situations meet needs of most vulnerable with CCCs.", "pcr_id": "6890/A0/05/202", "b": 0, "as_of": "07-31-17"}, {"sdt": "01-01-12", "otc_sfx": "003", "otc_id": 21761, "edt": "12-31-16", "dnr": {"all": 1668.0, "2": 1668.0}, "sct": {"all": 59957.0, "PA01-01": 59957.0}, "description": "By 2015, 88% of children under 1 year of age are immunized with pentavalent vaccine and 88% against measles.", "pcr_id": "6890/A0/05/102", "b": 0, "as_of": "07-31-17"}, {"sdt": "01-01-14", "otc_sfx": "002", "otc_id": 21882, "edt": "12-31-16", "dnr": {"all": 23949.0, "294": 23949.0}, "sct": {"all": 26061.0, "PA05-05": 26061.0}, "description": "Capacities developed for the implementation of strategic reforms in quality management and standards and teacher development", "pcr_id": "6890/A0/05/303", "b": 0, "as_of": "07-31-17"}, {"sdt": "01-01-17", "otc_sfx": "004", "otc_id": 22082, "edt": "12-31-20", "dnr": {"17": 164161.0, "all": 1379221.0, "2": 908500.0, "658": 306560.0}, "sct": {"all": 152887.0, "PA05-05": 152887.0}, "description": "By 2020 government educations officers at national, sub-national, and school levels have increased capacity to plan, manage,monitor, and apply policies and regulations", "pcr_id": "6890/A0/06/400", "b": 1643668.0, "as_of": "07-31-17"}, {"sdt": "01-01-12", "otc_sfx": "002", "otc_id": 21986, "edt": "12-31-16", "dnr": {"24": 5318.0, "all": 240652.0, "2": 235334.0}, "sct": {"all": 210161.0, "PA04-06": 511.0, "PA04-01": 69.0, "PA07-02": 542.0, "PA07-03": 185.0, "PA07-04": 85.0, "PA07-05": 189.0, "PA06-07": 175.0, "PA06-06": 47.0, "PA06-05": 1195.0, "PA06-04": 142.0, "PA06-03": 199.0, "PA06-02": 262.0, "PA01-05": 533.0, "PA06-08": 410.0, "PA04-05": 357.0, "PA04-04": 31.0, "PA01-01": 172.0, "PA01-06": 3.0, "PA01-07": 140.0, "PA01-04": 1112.0, "PA04-02": 171.0, "PA03-04": 124.0, "PA03-05": 138.0, "PA03-06": 53539.0, "PA03-01": 1430.0, "PA03-02": 146702.0, "PA05-04": 154.0, "PA05-05": 434.0, "PA05-02": 242.0, "PA05-03": 93.0, "PA05-01": 268.0, "PA01-03": 216.0, "PA02-03": 35.0, "PA02-02": 207.0, "PA02-01": 49.0}, "description": "Sector partners with strengthened capacities, in particular in the areas of planning, procurement and M&E to implement WASHprogrammes.", "pcr_id": "6890/A0/05/201", "b": 0, "as_of": "07-31-17"}, {"sdt": "01-01-17", "otc_sfx": "003", "otc_id": 22078, "edt": "12-31-20", "dnr": {"all": 3488735.0, "195": 193070.0, "1540": 119600.0, "294": 775766.0, "9": 305252.0, "11": 174445.0, "2": 763000.0, "13": 373960.0, "658": 351120.0, "73": 110000.0, "1785": 196420.0, "28": 30000.0, "61": 96102.0}, "sct": {"all": 443506.0, "PA05-02": 196724.0, "PA05-04": 246782.0}, "description": "By 2020, School councils and communities have improved accountability to prevent drop-out and absenteeism with special focus onadolescent girls, children with disabilities and children affected by conflict/disaster", "pcr_id": "6890/A0/06/400", "b": 2511317.0, "as_of": "07-31-17"}, {"sdt": "01-01-12", "otc_sfx": "001", "otc_id": 21970, "edt": "12-31-16", "dnr": {"24": 538.0, "all": 127776.0, "468": 71165.0, "2": 56073.0}, "sct": {"all": 542191.0, "PA04-06": 23367.0, "PA07-02": 3950.0, "PA07-03": 22182.0, "PA07-04": 16539.0, "PA07-05": 24628.0, "PA06-07": 7103.0, "PA06-06": 5857.0, "PA06-05": 21270.0, "PA06-04": 27647.0, "PA06-03": 13611.0, "PA06-02": 1039.0, "PA06-08": 15657.0, "PA04-05": 4215.0, "PA04-04": 2094.0, "PA01-01": 2399.0, "PA01-06": 140.0, "PA01-04": 28139.0, "PA01-05": 27682.0, "PA03-04": 10552.0, "PA03-05": 901.0, "PA03-06": 72278.0, "PA03-01": 9018.0, "PA03-02": 27613.0, "PA05-04": 6632.0, "PA05-05": 41527.0, "PA05-02": 28842.0, "PA05-03": 13509.0, "PA05-01": 28976.0, "PA01-03": 13688.0, "PA02-03": 2584.0, "PA02-02": 28234.0, "PA02-01": 10318.0}, "description": "Strengthened sector coordination mechanisms through the SWAp and other fora to ensure national budgets, policies, strategies andM&E plans prioritize vulnerable groups to reduce disparities in WASH service access", "pcr_id": "6890/A0/05/201", "b": 0, "as_of": "07-31-17"}, {"sdt": "01-01-12", "otc_sfx": "007", "otc_id": 21860, "edt": "12-31-16", "dnr": {"all": 379745.0, "2": 379745.0}, "sct": {"PA02-02": 249514.0, "all": 350354.0, "PA02-01": 100840.0}, "description": "By 2015, 80% of children living with HIV have access to quality care, treatment and nutritional services", "pcr_id": "6890/A0/05/102", "b": 0, "as_of": "07-31-17"}, {"sdt": "01-01-12", "otc_sfx": "002", "otc_id": 21768, "edt": "07-14-14", "dnr": {"all": 0}, "sct": {"all": 3155.0, "PA03-01": 3155.0}, "description": "At least 770,000 new users (550,000 rural, 220,000 small towns), prioritising vulnerable groups, have access to and use safe waterand 480,000 people (350,000 rural and 130,000 small towns) have access to and use safe sanitation and improved hygiene practices..", "pcr_id": "6890/A0/05/202", "b": 0, "as_of": "07-31-17"}], "year": 2017}